sc_retail_client_analysis/__init__.py
sc_retail_client_analysis/main.py
sc_retail_client_analysis/analyzer/__init__.py
sc_retail_client_analysis/analyzer/base/__init__.py
sc_retail_client_analysis/analyzer/base/base_analyzer.py
sc_retail_client_analysis/analyzer/client/__init__.py
sc_retail_client_analysis/analyzer/client/client_info_analyzer.py
sc_retail_client_analysis/tests/__init__.py
sc_retail_client_analysis/tests/sample_config/production.yml
test_data/__init__.py
test_data/client_info_base_analyzer.py
sc_retail_client_analysis-0.0.6.dist-info/LICENSE
sc_retail_client_analysis-0.0.6.dist-info/METADATA
sc_retail_client_analysis-0.0.6.dist-info/WHEEL
sc_retail_client_analysis-0.0.6.dist-info/entry_points.txt
sc_retail_client_analysis-0.0.6.dist-info/top_level.txt
sc_retail_client_analysis-0.0.6.dist-info/RECORD
