Metadata-Version: 2.1
Name: sc-retail-client-analysis
Version: 0.0.6
Summary: retail client info. analysis
Home-page: https://github.com/Scott-Lau/sc-retail-client-analysis
Author: Scott Lau
Author-email: exceedego@126.com
License: MIT
Keywords: python retail client info. analysis
Platform: POSIX
Classifier: Programming Language :: Python :: 3
Classifier: Programming Language :: Python :: 3.6
Classifier: Programming Language :: Python :: 3.7
Classifier: Programming Language :: Python :: 3.8
Classifier: Programming Language :: Python :: 3.9
Classifier: License :: OSI Approved :: MIT License
Classifier: Operating System :: OS Independent
Classifier: Topic :: Software Development
Classifier: Topic :: Utilities
Requires-Python: >=3.6
License-File: LICENSE
Requires-Dist: sc-utilities (>=0.0.11)
Requires-Dist: sc-config (>=0.0.11)
Requires-Dist: pandas (>=1.3.2)
Requires-Dist: openpyxl (>=3.0.10)
